{
  "users": [
    {
      "id": 1,
      "userName": "DChiapa",
      "img": "https://depor.com/resizer/4LiA3UcZpkTbq0pGF8j9dPiahkw=/580x330/smart/filters:format(jpeg):quality(75)/cloudfront-us-east-1.images.arcpublishing.com/elcomercio/6Y2EDIISGFGVFANEVDCR5LCG34.jpg",
      "rrss": [
        {
          "red": "Linkedin",
          "link": "https://www.linkedin.com/in/diegochiapa/"
        },
        { "red": "Github", "link": "https://github.com/dchiapa" }
      ]
    },
    {
      "id": 2,
      "userName": "kira",
      "img": "https://cdn.alfabetajuega.com/wp-content/uploads/2019/10/dragon-ball-goku-black.jpg",
      "rrss": [
        {
          "red": "linkedin",
          "link": "https://www.linkedin.com/in/jhonatanquirama/"
        },
        { "red": "github", "link": "https://github.com/kira4489" },
        { "red": "gitlab", "link": "https://gitlab.com/quiramapino347" }
      ]
    }
  ]
}
